[
    {
        "RPI": 1.2,
        "MS_VOL": 0.0660800674,
        "MS_VAL": 0.0785159826
    },
    {
        "RPI": 1.201,
        "MS_VOL": 0.0660272881,
        "MS_VAL": 0.0785191486
    },
    {
        "RPI": 1.202,
        "MS_VOL": 0.0659745087,
        "MS_VAL": 0.0785221906
    },
    {
        "RPI": 1.203,
        "MS_VOL": 0.0659217294,
        "MS_VAL": 0.0785251083
    },
    {
        "RPI": 1.204,
        "MS_VOL": 0.06586895,
        "MS_VAL": 0.078527902
    },
    {
        "RPI": 1.205,
        "MS_VOL": 0.0658116059,
        "MS_VAL": 0.0785241025
    },
    {
        "RPI": 1.206,
        "MS_VOL": 0.0657338719,
        "MS_VAL": 0.0784912482
    },
    {
        "RPI": 1.207,
        "MS_VOL": 0.0656561378,
        "MS_VAL": 0.0784582111
    },
    {
        "RPI": 1.208,
        "MS_VOL": 0.0655714799,
        "MS_VAL": 0.0784151546
    },
    {
        "RPI": 1.209,
        "MS_VOL": 0.065479485,
        "MS_VAL": 0.0783614666
    },
    {
        "RPI": 1.21,
        "MS_VOL": 0.0653736237,
        "MS_VAL": 0.07828783
    },
    {
        "RPI": 1.211,
        "MS_VOL": 0.0652587457,
        "MS_VAL": 0.0782011025
    },
    {
        "RPI": 1.212,
        "MS_VOL": 0.0650360355,
        "MS_VAL": 0.0779604014
    },
    {
        "RPI": 1.213,
        "MS_VOL": 0.0648021156,
        "MS_VAL": 0.0777031852
    },
    {
        "RPI": 1.214,
        "MS_VOL": 0.0645681958,
        "MS_VAL": 0.0774454188
    },
    {
        "RPI": 1.215,
        "MS_VOL": 0.064334276,
        "MS_VAL": 0.0771871022
    },
    {
        "RPI": 1.216,
        "MS_VOL": 0.0641003562,
        "MS_VAL": 0.0769282354
    },
    {
        "RPI": 1.217,
        "MS_VOL": 0.0638664363,
        "MS_VAL": 0.0766688184
    },
    {
        "RPI": 1.218,
        "MS_VOL": 0.0636325165,
        "MS_VAL": 0.0764088511
    },
    {
        "RPI": 1.219,
        "MS_VOL": 0.0633985967,
        "MS_VAL": 0.0761483337
    },
    {
        "RPI": 1.22,
        "MS_VOL": 0.0629785955,
        "MS_VAL": 0.0756202762
    },
    {
        "RPI": 1.221,
        "MS_VOL": 0.0624358026,
        "MS_VAL": 0.0749149043
    },
    {
        "RPI": 1.222,
        "MS_VOL": 0.0619082875,
        "MS_VAL": 0.0742302125
    },
    {
        "RPI": 1.223,
        "MS_VOL": 0.0613807725,
        "MS_VAL": 0.0735442799
    },
    {
        "RPI": 1.224,
        "MS_VOL": 0.0608532574,
        "MS_VAL": 0.0728571065
    },
    {
        "RPI": 1.225,
        "MS_VOL": 0.0603870965,
        "MS_VAL": 0.0722570842
    },
    {
        "RPI": 1.226,
        "MS_VOL": 0.0599454049,
        "MS_VAL": 0.0716912466
    },
    {
        "RPI": 1.227,
        "MS_VOL": 0.0595639446,
        "MS_VAL": 0.071211286
    },
    {
        "RPI": 1.228,
        "MS_VOL": 0.0592702474,
        "MS_VAL": 0.0708571765
    },
    {
        "RPI": 1.229,
        "MS_VOL": 0.0589765501,
        "MS_VAL": 0.0705023761
    },
    {
        "RPI": 1.23,
        "MS_VOL": 0.0586897261,
        "MS_VAL": 0.0701568275
    },
    {
        "RPI": 1.231,
        "MS_VOL": 0.0583951698,
        "MS_VAL": 0.06979941
    },
    {
        "RPI": 1.232,
        "MS_VOL": 0.0582207517,
        "MS_VAL": 0.0696153697
    },
    {
        "RPI": 1.233,
        "MS_VOL": 0.0580576632,
        "MS_VAL": 0.069447348
    },
    {
        "RPI": 1.234,
        "MS_VOL": 0.0578945747,
        "MS_VAL": 0.0692789428
    },
    {
        "RPI": 1.235,
        "MS_VOL": 0.0577314862,
        "MS_VAL": 0.0691101539
    },
    {
        "RPI": 1.236,
        "MS_VOL": 0.0577187837,
        "MS_VAL": 0.0691595854
    },
    {
        "RPI": 1.237,
        "MS_VOL": 0.0577476849,
        "MS_VAL": 0.069269512
    },
    {
        "RPI": 1.238,
        "MS_VOL": 0.0577765862,
        "MS_VAL": 0.0693795065
    },
    {
        "RPI": 1.239,
        "MS_VOL": 0.0578054874,
        "MS_VAL": 0.069489569
    },
    {
        "RPI": 1.24,
        "MS_VOL": 0.0578200454,
        "MS_VAL": 0.0695787824
    },
    {
        "RPI": 1.241,
        "MS_VOL": 0.0578220605,
        "MS_VAL": 0.0696497237
    },
    {
        "RPI": 1.242,
        "MS_VOL": 0.0578240756,
        "MS_VAL": 0.0697206698
    },
    {
        "RPI": 1.243,
        "MS_VOL": 0.0578260908,
        "MS_VAL": 0.0697916207
    },
    {
        "RPI": 1.244,
        "MS_VOL": 0.0578281059,
        "MS_VAL": 0.0698625762
    },
    {
        "RPI": 1.245,
        "MS_VOL": 0.057830121,
        "MS_VAL": 0.0699335366
    },
    {
        "RPI": 1.246,
        "MS_VOL": 0.0578321362,
        "MS_VAL": 0.0700045016
    },
    {
        "RPI": 1.247,
        "MS_VOL": 0.0578341513,
        "MS_VAL": 0.0700754714
    },
    {
        "RPI": 1.248,
        "MS_VOL": 0.0578361664,
        "MS_VAL": 0.0701464459
    },
    {
        "RPI": 1.249,
        "MS_VOL": 0.0578381816,
        "MS_VAL": 0.0702174252
    },
    {
        "RPI": 1.25,
        "MS_VOL": 0.0578401967,
        "MS_VAL": 0.0702884092
    },
    {
        "RPI": 1.251,
        "MS_VOL": 0.0578472625,
        "MS_VAL": 0.0703668288
    },
    {
        "RPI": 1.252,
        "MS_VOL": 0.0578544294,
        "MS_VAL": 0.0704454139
    },
    {
        "RPI": 1.253,
        "MS_VOL": 0.0578615963,
        "MS_VAL": 0.0705240159
    },
    {
        "RPI": 1.254,
        "MS_VOL": 0.0578687633,
        "MS_VAL": 0.0706026348
    },
    {
        "RPI": 1.255,
        "MS_VOL": 0.0578759302,
        "MS_VAL": 0.0706812705
    },
    {
        "RPI": 1.256,
        "MS_VOL": 0.0578830972,
        "MS_VAL": 0.0707599231
    },
    {
        "RPI": 1.257,
        "MS_VOL": 0.0578902641,
        "MS_VAL": 0.0708385925
    },
    {
        "RPI": 1.258,
        "MS_VOL": 0.0578966168,
        "MS_VAL": 0.0709160741
    },
    {
        "RPI": 1.259,
        "MS_VOL": 0.0579027161,
        "MS_VAL": 0.0709931955
    },
    {
        "RPI": 1.26,
        "MS_VOL": 0.0579088155,
        "MS_VAL": 0.0710703313
    },
    {
        "RPI": 1.261,
        "MS_VOL": 0.0579149149,
        "MS_VAL": 0.0711474815
    },
    {
        "RPI": 1.262,
        "MS_VOL": 0.0579210142,
        "MS_VAL": 0.071224646
    },
    {
        "RPI": 1.263,
        "MS_VOL": 0.0579271136,
        "MS_VAL": 0.0713018248
    },
    {
        "RPI": 1.264,
        "MS_VOL": 0.0579332129,
        "MS_VAL": 0.071379018
    },
    {
        "RPI": 1.265,
        "MS_VOL": 0.0579393123,
        "MS_VAL": 0.0714562256
    },
    {
        "RPI": 1.266,
        "MS_VOL": 0.0579454117,
        "MS_VAL": 0.0715334475
    },
    {
        "RPI": 1.267,
        "MS_VOL": 0.057951511,
        "MS_VAL": 0.0716106837
    },
    {
        "RPI": 1.268,
        "MS_VOL": 0.0579576104,
        "MS_VAL": 0.0716879343
    },
    {
        "RPI": 1.269,
        "MS_VOL": 0.0579637098,
        "MS_VAL": 0.0717651992
    },
    {
        "RPI": 1.27,
        "MS_VOL": 0.0579698091,
        "MS_VAL": 0.0718424785
    }
]